AC_IaC/__init__.py
AC_IaC/command_line.py
AC_IaC/inference/full_pipe.py
AC_IaC/inference/pipe_base.py
AC_IaC/inference/sep_tok_pipe.py
AC_IaC/inference/spans_pipe.py
AC_IaC/inference/spans_pipe_visual.py
AC_IaC/training/README.md
AC_IaC/training/meta2latex.py
AC_IaC/training/meta_data.py
AC_IaC/training/test_dataset.py
AC_IaC/training/train.py
AC_IaC/training/train_diff.py
ac_iac-1.0.1.dist-info/METADATA
ac_iac-1.0.1.dist-info/WHEEL
ac_iac-1.0.1.dist-info/entry_points.txt
ac_iac-1.0.1.dist-info/licenses/LICENSE.txt
ac_iac-1.0.1.dist-info/RECORD
